[
{"nomeutente":"ale","oggettoAcquistato":"joypad","prezzoDiAcquisto":29.99}
,
{"nomeutente":"ale","oggettoAcquistato":"joypad","prezzoDiAcquisto":29.99}
,
{"nomeutente":"ale","oggettoAcquistato":"joypad","prezzoDiAcquisto":29.99}
,
{"nomeutente":"ale","oggettoAcquistato":"joypad","prezzoDiAcquisto":29.99}
,
{"nomeutente":"ale","oggettoAcquistato":"joypad","prezzoDiAcquisto":29.99}
,
{"nomeutente":"ale","oggettoAcquistato":"joypad","prezzoDiAcquisto":29.99}
,
{"nomeutente":"ale","oggettoAcquistato":"joypad","prezzoDiAcquisto":29.99}]
